[
    {
        "key": "dbln",
        "value": "%7B%22100010099516674%22%3A%22i7J8ZTa6%22%2C%2261566729283364%22%3A%22xNHjapFD%22%7D",
        "domain": "facebook.com",
        "path": "/login/device-based/",
        "hostOnly": false,
        "creation": "2025-04-17T00:22:04.003Z",
        "lastAccessed": "2025-04-17T00:22:04.003Z"
    },
    {
        "key": "datr",
        "value": "x7z1Z_icKJnzuXJTyPmrk3rR",
        "domain": "facebook.com",
        "path": "/",
        "hostOnly": false,
        "creation": "2025-04-17T00:22:04.003Z",
        "lastAccessed": "2025-04-17T00:22:04.003Z"
    },
    {
        "key": "sb",
        "value": "x7z1Z10k3d7u-YXLL5tclCLl",
        "domain": "facebook.com",
        "path": "/",
        "hostOnly": false,
        "creation": "2025-04-17T00:22:04.003Z",
        "lastAccessed": "2025-04-17T00:22:04.003Z"
    },
    {
        "key": "dpr",
        "value": "1.635840654373169",
        "domain": "facebook.com",
        "path": "/",
        "hostOnly": false,
        "creation": "2025-04-17T00:22:04.003Z",
        "lastAccessed": "2025-04-17T00:22:04.003Z"
    },
    {
        "key": "ps_l",
        "value": "1",
        "domain": "facebook.com",
        "path": "/",
        "hostOnly": false,
        "creation": "2025-04-17T00:22:04.003Z",
        "lastAccessed": "2025-04-17T00:22:04.003Z"
    },
    {
        "key": "ps_n",
        "value": "1",
        "domain": "facebook.com",
        "path": "/",
        "hostOnly": false,
        "creation": "2025-04-17T00:22:04.003Z",
        "lastAccessed": "2025-04-17T00:22:04.003Z"
    },
    {
        "key": "locale",
        "value": "en_US",
        "domain": "facebook.com",
        "path": "/",
        "hostOnly": false,
        "creation": "2025-04-17T00:22:04.003Z",
        "lastAccessed": "2025-04-17T00:22:04.003Z"
    },
    {
        "key": "m_pixel_ratio",
        "value": "1.4878759384155273",
        "domain": "facebook.com",
        "path": "/",
        "hostOnly": false,
        "creation": "2025-04-17T00:22:04.003Z",
        "lastAccessed": "2025-04-17T00:22:04.003Z"
    },
    {
        "key": "wd",
        "value": "485x912",
        "domain": "facebook.com",
        "path": "/",
        "hostOnly": false,
        "creation": "2025-04-17T00:22:04.003Z",
        "lastAccessed": "2025-04-17T00:22:04.003Z"
    },
    {
        "key": "c_user",
        "value": "61566729283364",
        "domain": "facebook.com",
        "path": "/",
        "hostOnly": false,
        "creation": "2025-04-17T00:22:04.003Z",
        "lastAccessed": "2025-04-17T00:22:04.003Z"
    },
    {
        "key": "fr",
        "value": "0XrAuoo2AC3ajPahU.AWe88tY3VJ7hnEYwF0zcSItZkmLYBbfPJDTspI8FpfNX-38cLxs.Bn9bzH..AAA.0.0.BoAEmf.AWfOOLUHyqsZ1q2Dwuti5QHK8Nc",
        "domain": "facebook.com",
        "path": "/",
        "hostOnly": false,
        "creation": "2025-04-17T00:22:04.003Z",
        "lastAccessed": "2025-04-17T00:22:04.003Z"
    },
    {
        "key": "xs",
        "value": "37%3A6lwO5pt8JOlmFg%3A2%3A1744849311%3A-1%3A7867",
        "domain": "facebook.com",
        "path": "/",
        "hostOnly": false,
        "creation": "2025-04-17T00:22:04.003Z",
        "lastAccessed": "2025-04-17T00:22:04.003Z"
    },
    {
        "key": "fbl_st",
        "value": "100628112%3BT%3A29080821",
        "domain": "facebook.com",
        "path": "/",
        "hostOnly": false,
        "creation": "2025-04-17T00:22:04.003Z",
        "lastAccessed": "2025-04-17T00:22:04.003Z"
    },
    {
        "key": "vpd",
        "value": "v1%3B775x412x1.4878759384155273",
        "domain": "facebook.com",
        "path": "/",
        "hostOnly": false,
        "creation": "2025-04-17T00:22:04.003Z",
        "lastAccessed": "2025-04-17T00:22:04.003Z"
    },
    {
        "key": "wl_cbv",
        "value": "v2%3Bclient_version%3A2790%3Btimestamp%3A1744849313%3BCRCM%3A514197562",
        "domain": "facebook.com",
        "path": "/",
        "hostOnly": false,
        "creation": "2025-04-17T00:22:04.003Z",
        "lastAccessed": "2025-04-17T00:22:04.003Z"
    }
]
